{"chunk_definitions":[{"row":25,"row_count":1,"visible":true,"expansion_state":0,"options":{"engine":"r","label":"unnamed-chunk-3"},"document_id":"9FFFACF5","chunk_id":"c0p4s4afqqa6i","chunk_label":"unnamed-chunk-2"},{"row":34,"row_count":1,"visible":true,"expansion_state":0,"options":{"engine":"r","label":"unnamed-chunk-2"},"document_id":"9FFFACF5","chunk_id":"cswc0s974coyu","chunk_label":"unnamed-chunk-3"},{"row":48,"row_count":1,"visible":true,"expansion_state":0,"options":{"engine":"r","label":"unnamed-chunk-3"},"document_id":"9FFFACF5","chunk_id":"cgqng6e79tsrq","chunk_label":"unnamed-chunk-4"},{"row":61,"row_count":1,"visible":true,"expansion_state":0,"options":{"engine":"r","label":"unnamed-chunk-3"},"document_id":"9FFFACF5","chunk_id":"coth34y5xsc0v","chunk_label":"unnamed-chunk-6"},{"row":73,"row_count":1,"visible":true,"expansion_state":0,"options":{"engine":"r","label":"unnamed-chunk-7"},"document_id":"9FFFACF5","chunk_id":"ck3n574xj84dr","chunk_label":"unnamed-chunk-7"},{"row":82,"row_count":1,"visible":true,"expansion_state":0,"options":{"engine":"r","label":"unnamed-chunk-1"},"document_id":"9FFFACF5","chunk_id":"czce1a2gfjzwo","chunk_label":"unnamed-chunk-8"},{"row":116,"row_count":1,"visible":true,"expansion_state":0,"options":{"engine":"r","label":"unnamed-chunk-5"},"document_id":"9FFFACF5","chunk_id":"caat1hqogx41y","chunk_label":"unnamed-chunk-11"},{"row":125,"row_count":1,"visible":true,"expansion_state":0,"options":{"engine":"r","label":"unnamed-chunk-2"},"document_id":"9FFFACF5","chunk_id":"c6gxcmjbr1w9k","chunk_label":"unnamed-chunk-12"},{"row":156,"row_count":1,"visible":true,"expansion_state":0,"options":{"engine":"r","label":"unnamed-chunk-5"},"document_id":"9FFFACF5","chunk_id":"c8g0ybl2g6vvy","chunk_label":"unnamed-chunk-14"},{"row":164,"row_count":1,"visible":true,"expansion_state":0,"options":{"engine":"r","label":"unnamed-chunk-6"},"document_id":"9FFFACF5","chunk_id":"cuqibc1qv0bqk","chunk_label":"unnamed-chunk-15"},{"row":216,"row_count":1,"visible":true,"expansion_state":0,"options":{"engine":"r","label":"unnamed-chunk-4"},"document_id":"9FFFACF5","chunk_id":"ctdyw5naif92e","chunk_label":"unnamed-chunk-16"},{"row":229,"row_count":1,"visible":true,"expansion_state":0,"options":{"engine":"r","label":"unnamed-chunk-6"},"document_id":"9FFFACF5","chunk_id":"c0kuee7vg557r","chunk_label":"unnamed-chunk-17"},{"row":239,"row_count":1,"visible":true,"expansion_state":0,"options":{"engine":"r","label":"unnamed-chunk-7"},"document_id":"9FFFACF5","chunk_id":"cb261yppis0fu","chunk_label":"unnamed-chunk-18"},{"row":256,"row_count":1,"visible":true,"expansion_state":0,"options":{"engine":"r","label":"unnamed-chunk-8"},"document_id":"9FFFACF5","chunk_id":"cwr2vgnc1olfc","chunk_label":"unnamed-chunk-19"},{"row":265,"row_count":1,"visible":true,"expansion_state":0,"options":{"engine":"r","label":"unnamed-chunk-9"},"document_id":"9FFFACF5","chunk_id":"c3wr8t63u6kxn","chunk_label":"unnamed-chunk-20"}],"doc_write_time":1698418436,"chunk_rendered_width":400}